<?xml version="1.0" encoding="UTF-8"?><xml><owner_type>orgs</owner_type><package_type>container</package_type><owner_id>651467</owner_id><owner>splunk</owner><repo>splunk-connect-for-syslog</repo><package>splunk-connect-for-syslog%2Fcontainer3</package><date>2024-12-28</date><size>551.8 MB</size><versions>17</versions><tagged>16</tagged><downloads>39.6M</downloads><downloads_month>1</downloads_month><downloads_week>0</downloads_week><downloads_day>0</downloads_day><raw_size>551871785</raw_size><raw_versions>17</raw_versions><raw_tagged>16</raw_tagged><raw_downloads>39622392</raw_downloads><raw_downloads_month>1</raw_downloads_month><raw_downloads_week>0</raw_downloads_week><raw_downloads_day>0</raw_downloads_day><version><id>-1</id><name>latest</name><date>2024-12-28</date><newest>true</newest><latest>true</latest><size>551.8 MB</size><downloads>39.6M</downloads><downloads_month>1</downloads_month><downloads_week>0</downloads_week><downloads_day>0</downloads_day><raw_size>551871785</raw_size><raw_downloads>39622392</raw_downloads><raw_downloads_month>1</raw_downloads_month><raw_downloads_week>0</raw_downloads_week><raw_downloads_day>0</raw_downloads_day><tags></tags></version></xml>
