{"owner_type":"users","package_type":"container","owner_id":2321814,"owner":"the-maldridge","repo":"yurt-tools","package":"yurt-tools","date":"2024-12-30","size":"7.7 MB","versions":"9","tagged":"9","downloads":"6.1k","downloads_month":"0","downloads_week":"0","downloads_day":"0","raw_size":7701980,"raw_versions":9,"raw_tagged":9,"raw_downloads":6108,"raw_downloads_month":0,"raw_downloads_week":0,"raw_downloads_day":0,"version":[{"id":-1,"name":"latest","date":"2024-12-30","newest":true,"latest":true,"size":"7.7 MB","downloads":"6.1k","downloads_month":"0","downloads_week":"0","downloads_day":"0","raw_size":7701980,"raw_downloads":6108,"raw_downloads_month":0,"raw_downloads_week":0,"raw_downloads_day":0,"tags":[""]}]}
