{"owner_type":"orgs","package_type":"container","owner_id":21021,"owner":"soundcloud","repo":"airflow","package":"airflow%2Fmaster-python3.8-ci","date":"2024-12-29","size":"889.9 MB","versions":"14","tagged":"14","downloads":"2.2k","downloads_month":"0","downloads_week":"0","downloads_day":"0","raw_size":889960690,"raw_versions":14,"raw_tagged":14,"raw_downloads":2222,"raw_downloads_month":0,"raw_downloads_week":0,"raw_downloads_day":0,"version":[{"id":-1,"name":"latest","date":"2024-12-29","newest":true,"latest":true,"size":"889.9 MB","downloads":"2.2k","downloads_month":"0","downloads_week":"0","downloads_day":"0","raw_size":889960690,"raw_downloads":2222,"raw_downloads_month":0,"raw_downloads_week":0,"raw_downloads_day":0,"tags":[""]}]}
